odoo/addons/web_quick_start_screen/README.rst
odoo/addons/web_quick_start_screen/__init__.py
odoo/addons/web_quick_start_screen/__manifest__.py
odoo/addons/web_quick_start_screen/demo/quick_screen_action_demo_data.xml
odoo/addons/web_quick_start_screen/i18n/es.po
odoo/addons/web_quick_start_screen/i18n/it.po
odoo/addons/web_quick_start_screen/i18n/web_quick_start_screen.pot
odoo/addons/web_quick_start_screen/models/__init__.py
odoo/addons/web_quick_start_screen/models/quick_start_screen.py
odoo/addons/web_quick_start_screen/models/quick_start_screen_action.py
odoo/addons/web_quick_start_screen/models/res_users.py
odoo/addons/web_quick_start_screen/readme/CONFIGURE.md
odoo/addons/web_quick_start_screen/readme/CONTEXT.md
odoo/addons/web_quick_start_screen/readme/CONTRIBUTORS.md
odoo/addons/web_quick_start_screen/readme/DESCRIPTION.md
odoo/addons/web_quick_start_screen/readme/ROADMAP.md
odoo/addons/web_quick_start_screen/readme/USAGE.md
odoo/addons/web_quick_start_screen/security/ir.model.access.csv
odoo/addons/web_quick_start_screen/security/security.xml
odoo/addons/web_quick_start_screen/static/description/icon.png
odoo/addons/web_quick_start_screen/static/description/icon.svg
odoo/addons/web_quick_start_screen/static/description/index.html
odoo/addons/web_quick_start_screen/static/src/js/kanban_controller.esm.js
odoo/addons/web_quick_start_screen/static/src/js/start_screen_control_panel.xml
odoo/addons/web_quick_start_screen/static/src/scss/quick_start_screen.scss
odoo/addons/web_quick_start_screen/tests/__init__.py
odoo/addons/web_quick_start_screen/tests/test_web_quick_start_screen.py
odoo/addons/web_quick_start_screen/views/quick_screen_action_view.xml
odoo/addons/web_quick_start_screen/views/quick_start_screen_views.xml
odoo/addons/web_quick_start_screen/views/res_users_views.xml
odoo_addon_web_quick_start_screen-18.0.1.0.0.4.dist-info/METADATA
odoo_addon_web_quick_start_screen-18.0.1.0.0.4.dist-info/WHEEL
odoo_addon_web_quick_start_screen-18.0.1.0.0.4.dist-info/top_level.txt
odoo_addon_web_quick_start_screen-18.0.1.0.0.4.dist-info/RECORD
